{
  "UseSeasonalMaps": true,
  "MinimapBlacklist": [],
  "MenuKey": "Tab",
  "TooltipKey": "Space",
  "MinimapDragKey": "LeftControl",
  "MinimapToggleKey": "OemPipe",
  "ShowFarmBuildings": true,
  "ShowChildren": false,
  "ShowHorse": true,
  "CustomNpcMarkerOffsets": {
    "Alesia": 2,
    "Andy": 0,
    "Apples": 16,
    "Camilla": 2,
    "Claire_Joja": 3,
    "Isaac": 0,
    "MarlonFay": 2,
    "Morgan": 8,
    "Olivia": 1,
    "Victor": 0,
    "Scarlett": 4,
    "Sophia": 3,
    "Susan": 1
  },
  "NpcBlackList": [],
  "DEBUG_MODE": false
}